{
  "step": "step3_5",
  "keyword": "自動車整備士採用難しい",
  "emotional_analysis": {
    "primary_emotion": "焦り",
    "secondary_emotions": [
      "不安",
      " frustrated",
      "期待"
    ],
    "pain_points": [
      "求人広告を出しても応募が来ない",
      "採用コストばかりがかさんでいる",
      "採用してもすぐに辞めてしまう"
    ],
    "desires": [
      "優秀な整備士を採用したい",
      "採用コストを抑えたい",
      "従業員が長く働いてくれる職場を作りたい"
    ]
  },
  "human_touch_patterns": [
    {
      "type": "experience",
      "content": "「今日も一日、求人サイトをチェックする田中人事。しかし、応募者はゼロ。溜息をつきながら、また明日も同じ作業を繰り返すのか…と気が重くなる。」",
      "placement_suggestion": "導入部分"
    },
    {
      "type": "emotion",
      "content": "「採用がうまくいかない焦り、将来への不安… そのお気持ち、痛いほどよく分かります。」",
      "placement_suggestion": "問題提起の後"
    },
    {
      "type": "empathy",
      "content": "「でも、諦めないでください。必ず、光は見えてきます。共に、この難局を乗り越えましょう。」",
      "placement_suggestion": "解決策の前"
    }
  ],
  "experience_episodes": [
    {
      "scenario": "新人整備士の早期離職",
      "narrative": "「入社3ヶ月の佐藤くん。最初はやる気に満ち溢れていましたが、最近元気がありません。話を聞くと、業務の忙しさに加え、教育体制の不備に不満を感じているとのこと。結局、1ヶ月後に退職してしまいました。」",
      "lesson": "採用後の育成体制の重要性。早期離職を防ぐためには、手厚いフォローとキャリアパスの提示が不可欠。"
    },
    {
      "scenario": "ベテラン整備士の退職",
      "narrative": "「長年工場を支えてくれたベテランの鈴木さんが、ついに引退。彼の技術力は工場の宝でしたが、後継者が育っておらず、顧客からの信頼を失う危機に。後任探しも難航しています。」",
      "lesson": "技術継承の重要性。ベテランの技術を若い世代に伝える仕組み作りが急務。"
    },
    {
      "scenario": "求人広告の効果の低下",
      "narrative": "「以前は効果のあった求人広告。しかし、最近は応募が激減。原因を調べてみると、若者の車離れや、整備士の仕事に対するネガティブなイメージが影響していることが分かりました。」",
      "lesson": "求人広告の見直し。ターゲット層に合わせた魅力的な情報発信が重要。"
    }
  ],
  "emotional_hooks": [
    "「採用難を乗り越え、未来の整備工場を創るために…」",
    "「もう、一人で悩まないでください。成功への道筋を、今、明らかにします。」"
  ],
  "phase_emotional_map": {
    "phase1": {
      "dominant_emotion": "",
      "empathy_statements": [],
      "experience_episodes": []
    },
    "phase2": {
      "dominant_emotion": "",
      "empathy_statements": [],
      "experience_episodes": []
    },
    "phase3": {
      "dominant_emotion": "",
      "empathy_statements": [],
      "experience_episodes": []
    }
  },
  "behavioral_economics_hooks": {
    "loss_aversion_hook": "",
    "social_proof_hook": "",
    "authority_hook": "",
    "scarcity_hook": ""
  },
  "placement_instructions": [],
  "raw_output": "```json\n{\n  \"emotional_analysis\": {\n    \"primary_emotion\": \"焦り\",\n    \"secondary_emotions\": [\"不安\", \" frustrated\", \"期待\"],\n    \"pain_points\": [\"求人広告を出しても応募が来ない\", \"採用コストばかりがかさんでいる\", \"採用してもすぐに辞めてしまう\"],\n    \"desires\": [\"優秀な整備士を採用したい\", \"採用コストを抑えたい\", \"従業員が長く働いてくれる職場を作りたい\"]\n  },\n  \"human_touch_patterns\": [\n    {\n      \"type\": \"experience\",\n      \"content\": \"「今日も一日、求人サイトをチェックする田中人事。しかし、応募者はゼロ。溜息をつきながら、また明日も同じ作業を繰り返すのか…と気が重くなる。」\",\n      \"placement_suggestion\": \"導入部分\"\n    },\n    {\n      \"type\": \"emotion\",\n      \"content\": \"「採用がうまくいかない焦り、将来への不安… そのお気持ち、痛いほどよく分かります。」\",\n      \"placement_suggestion\": \"問題提起の後\"\n    },\n    {\n      \"type\": \"empathy\",\n      \"content\": \"「でも、諦めないでください。必ず、光は見えてきます。共に、この難局を乗り越えましょう。」\",\n      \"placement_suggestion\": \"解決策の前\"\n    }\n  ],\n  \"experience_episodes\": [\n    {\n      \"scenario\": \"新人整備士の早期離職\",\n      \"narrative\": \"「入社3ヶ月の佐藤くん。最初はやる気に満ち溢れていましたが、最近元気がありません。話を聞くと、業務の忙しさに加え、教育体制の不備に不満を感じているとのこと。結局、1ヶ月後に退職してしまいました。」\",\n      \"lesson\": \"採用後の育成体制の重要性。早期離職を防ぐためには、手厚いフォローとキャリアパスの提示が不可欠。\"\n    },\n    {\n      \"scenario\": \"ベテラン整備士の退職\",\n      \"narrative\": \"「長年工場を支えてくれたベテランの鈴木さんが、ついに引退。彼の技術力は工場の宝でしたが、後継者が育っておらず、顧客からの信頼を失う危機に。後任探しも難航しています。」\",\n      \"lesson\": \"技術継承の重要性。ベテランの技術を若い世代に伝える仕組み作りが急務。\"\n    },\n    {\n      \"scenario\": \"求人広告の効果の低下\",\n      \"narrative\": \"「以前は効果のあった求人広告。しかし、最近は応募が激減。原因を調べてみると、若者の車離れや、整備士の仕事に対するネガティブなイメージが影響していることが分かりました。」\",\n      \"lesson\": \"求人広告の見直し。ターゲット層に合わせた魅力的な情報発信が重要。\"\n    }\n  ],\n  \"emotional_hooks\": [\n    \"「採用難を乗り越え、未来の整備工場を創るために…」\",\n    \"「もう、一人で悩まないでください。成功への道筋を、今、明らかにします。」\",\n    \"「採用コストを大幅削減！その秘策を、こっそり教えます。」\n  ]\n}\n```",
  "parsed_data": {
    "emotional_analysis": {
      "primary_emotion": "焦り",
      "secondary_emotions": [
        "不安",
        " frustrated",
        "期待"
      ],
      "pain_points": [
        "求人広告を出しても応募が来ない",
        "採用コストばかりがかさんでいる",
        "採用してもすぐに辞めてしまう"
      ],
      "desires": [
        "優秀な整備士を採用したい",
        "採用コストを抑えたい",
        "従業員が長く働いてくれる職場を作りたい"
      ]
    },
    "human_touch_patterns": [
      {
        "type": "experience",
        "content": "「今日も一日、求人サイトをチェックする田中人事。しかし、応募者はゼロ。溜息をつきながら、また明日も同じ作業を繰り返すのか…と気が重くなる。」",
        "placement_suggestion": "導入部分"
      },
      {
        "type": "emotion",
        "content": "「採用がうまくいかない焦り、将来への不安… そのお気持ち、痛いほどよく分かります。」",
        "placement_suggestion": "問題提起の後"
      },
      {
        "type": "empathy",
        "content": "「でも、諦めないでください。必ず、光は見えてきます。共に、この難局を乗り越えましょう。」",
        "placement_suggestion": "解決策の前"
      }
    ],
    "experience_episodes": [
      {
        "scenario": "新人整備士の早期離職",
        "narrative": "「入社3ヶ月の佐藤くん。最初はやる気に満ち溢れていましたが、最近元気がありません。話を聞くと、業務の忙しさに加え、教育体制の不備に不満を感じているとのこと。結局、1ヶ月後に退職してしまいました。」",
        "lesson": "採用後の育成体制の重要性。早期離職を防ぐためには、手厚いフォローとキャリアパスの提示が不可欠。"
      },
      {
        "scenario": "ベテラン整備士の退職",
        "narrative": "「長年工場を支えてくれたベテランの鈴木さんが、ついに引退。彼の技術力は工場の宝でしたが、後継者が育っておらず、顧客からの信頼を失う危機に。後任探しも難航しています。」",
        "lesson": "技術継承の重要性。ベテランの技術を若い世代に伝える仕組み作りが急務。"
      },
      {
        "scenario": "求人広告の効果の低下",
        "narrative": "「以前は効果のあった求人広告。しかし、最近は応募が激減。原因を調べてみると、若者の車離れや、整備士の仕事に対するネガティブなイメージが影響していることが分かりました。」",
        "lesson": "求人広告の見直し。ターゲット層に合わせた魅力的な情報発信が重要。"
      }
    ],
    "emotional_hooks": [
      "「採用難を乗り越え、未来の整備工場を創るために…」",
      "「もう、一人で悩まないでください。成功への道筋を、今、明らかにします。」"
    ]
  },
  "metadata": {
    "generated_at": "2026-02-03T13:47:14.637023",
    "model": "gemini-2.0-flash",
    "model_config": {
      "platform": "gemini",
      "model": "gemini-2.0-flash"
    },
    "input_files": [
      "step0",
      "step1",
      "step3a",
      "step3b",
      "step3c",
      "step1_5"
    ]
  },
  "quality": {
    "attempts": 1,
    "issues": []
  },
  "token_usage": {
    "input": 16891,
    "output": 740
  },
  "output_path": "storage/dev-tenant-001/4d711f0b-58c6-4217-8325-cfd18b0d577b/step3_5/output.json",
  "output_digest": "c2fe0c30b5473fe2"
}