{
  "step": "step3_5",
  "keyword": "営業 採用 難しい",
  "emotional_analysis": {
    "primary_emotion": "焦り",
    "secondary_emotions": [
      "不安",
      "疲労"
    ],
    "pain_points": [
      "優秀な営業人材をなかなか採用できない",
      "採用してもすぐに辞めてしまう",
      "採用コストばかりがかさんで成果が出ない"
    ],
    "desires": [
      "自社の成長を加速させる優秀な営業チームを構築したい",
      "採用活動にかかる時間と労力を大幅に削減したい",
      "社員が長く活躍できる、魅力的な企業文化を醸成したい"
    ]
  },
  "human_touch_patterns": [
    {
      "type": "experience",
      "content": "「先日、ある企業の人事担当者の方とお話する機会がありました。『もう何ヶ月も営業職の募集をかけているのに、応募が全然来なくて…』と、本当に困り果てた様子でした。話を聞いていると、まさに今、この記事を読んでいるあなたと同じ悩みを抱えているようでした。」",
      "placement_suggestion": "導入部分"
    },
    {
      "type": "emotion",
      "content": "「採用がうまくいかない状況が続くと、本当に精神的に疲弊してしまいますよね。毎日、履歴書とにらめっこしながら、本当に自社に合う人材はどこにいるんだろう…と、途方に暮れてしまう気持ち、痛いほどよく分かります。」",
      "placement_suggestion": "問題提起の後"
    },
    {
      "type": "empathy",
      "content": "「でも、諦めないでください。営業職の採用は決して不可能ではありません。少し視点を変え、戦略を練り直すことで、必ず突破口は見つかります。この記事では、あなたの会社にぴったりの営業人材を見つけるためのヒントを、脳科学と行動経済学の視点も交えながら、具体的にお伝えしていきます。」",
      "placement_suggestion": "解決策の前"
    }
  ],
  "experience_episodes": [
    {
      "scenario": "中小企業の人事担当者が、なかなか営業職を採用できず、社長から毎日のようにプレッシャーをかけられている。",
      "narrative": "「社長からは『早く売上を上げられる人材を連れてこい！』と毎日怒鳴られる日々。求人広告の費用も底をつきそうで、正直、もうどうすればいいのか…。」",
      "lesson": "採用活動は、経営戦略と密接に連携している必要がある。現場の状況を理解し、適切な予算とサポート体制を整えることが重要。"
    },
    {
      "scenario": "大手企業の人事担当者が、高給を提示しても、優秀な営業人材から選ばれない。",
      "narrative": "「給与や福利厚生はどこよりも良いはずなのに、なぜか優秀な人材はうちを選んでくれない。企業文化やキャリアパスが魅力的でないのかもしれない…。」",
      "lesson": "給与だけでは優秀な人材は惹きつけられない。企業の理念やビジョン、キャリアパス、ワークライフバランスなど、総合的な魅力が必要。"
    },
    {
      "scenario": "スタートアップ企業の人事担当者が、知名度の低さから、応募者が集まらない。",
      "narrative": "「大手企業に比べて、どうしても知名度が低いので、応募者が集まらない。SNSを活用したり、社員の魅力を積極的に発信するなど、地道な活動が必要だと感じています。」",
      "lesson": "知名度が低い企業は、積極的に情報発信を行い、企業の魅力をアピールする必要がある。社員のエンゲージメントを高め、口コミを広げることも有効。"
    }
  ],
  "emotional_hooks": [
    "「なぜ、あなたの会社には優秀な営業マンが集まらないのか？その根本原因を脳科学で解き明かします。」",
    "「採用コストを30%削減し、定着率を2倍にする。そんな魔法のような採用戦略が存在します。」"
  ],
  "phase_emotional_map": {
    "phase1": {
      "dominant_emotion": "",
      "empathy_statements": [],
      "experience_episodes": []
    },
    "phase2": {
      "dominant_emotion": "",
      "empathy_statements": [],
      "experience_episodes": []
    },
    "phase3": {
      "dominant_emotion": "",
      "empathy_statements": [],
      "experience_episodes": []
    }
  },
  "behavioral_economics_hooks": {
    "loss_aversion_hook": "",
    "social_proof_hook": "",
    "authority_hook": "",
    "scarcity_hook": ""
  },
  "placement_instructions": [],
  "raw_output": "```json\n{\n  \"emotional_analysis\": {\n    \"primary_emotion\": \"焦り\",\n    \"secondary_emotions\": [\"不安\", \"疲労\"],\n    \"pain_points\": [\n      \"優秀な営業人材をなかなか採用できない\",\n      \"採用してもすぐに辞めてしまう\",\n      \"採用コストばかりがかさんで成果が出ない\"\n    ],\n    \"desires\": [\n      \"自社の成長を加速させる優秀な営業チームを構築したい\",\n      \"採用活動にかかる時間と労力を大幅に削減したい\",\n      \"社員が長く活躍できる、魅力的な企業文化を醸成したい\"\n    ]\n  },\n  \"human_touch_patterns\": [\n    {\n      \"type\": \"experience\",\n      \"content\": \"「先日、ある企業の人事担当者の方とお話する機会がありました。『もう何ヶ月も営業職の募集をかけているのに、応募が全然来なくて…』と、本当に困り果てた様子でした。話を聞いていると、まさに今、この記事を読んでいるあなたと同じ悩みを抱えているようでした。」\",\n      \"placement_suggestion\": \"導入部分\"\n    },\n    {\n      \"type\": \"emotion\",\n      \"content\": \"「採用がうまくいかない状況が続くと、本当に精神的に疲弊してしまいますよね。毎日、履歴書とにらめっこしながら、本当に自社に合う人材はどこにいるんだろう…と、途方に暮れてしまう気持ち、痛いほどよく分かります。」\",\n      \"placement_suggestion\": \"問題提起の後\"\n    },\n    {\n      \"type\": \"empathy\",\n      \"content\": \"「でも、諦めないでください。営業職の採用は決して不可能ではありません。少し視点を変え、戦略を練り直すことで、必ず突破口は見つかります。この記事では、あなたの会社にぴったりの営業人材を見つけるためのヒントを、脳科学と行動経済学の視点も交えながら、具体的にお伝えしていきます。」\",\n      \"placement_suggestion\": \"解決策の前\"\n    }\n  ],\n  \"experience_episodes\": [\n    {\n      \"scenario\": \"中小企業の人事担当者が、なかなか営業職を採用できず、社長から毎日のようにプレッシャーをかけられている。\",\n      \"narrative\": \"「社長からは『早く売上を上げられる人材を連れてこい！』と毎日怒鳴られる日々。求人広告の費用も底をつきそうで、正直、もうどうすればいいのか…。」\",\n      \"lesson\": \"採用活動は、経営戦略と密接に連携している必要がある。現場の状況を理解し、適切な予算とサポート体制を整えることが重要。\"\n    },\n    {\n      \"scenario\": \"大手企業の人事担当者が、高給を提示しても、優秀な営業人材から選ばれない。\",\n      \"narrative\": \"「給与や福利厚生はどこよりも良いはずなのに、なぜか優秀な人材はうちを選んでくれない。企業文化やキャリアパスが魅力的でないのかもしれない…。」\",\n      \"lesson\": \"給与だけでは優秀な人材は惹きつけられない。企業の理念やビジョン、キャリアパス、ワークライフバランスなど、総合的な魅力が必要。\"\n    },\n    {\n      \"scenario\": \"スタートアップ企業の人事担当者が、知名度の低さから、応募者が集まらない。\",\n      \"narrative\": \"「大手企業に比べて、どうしても知名度が低いので、応募者が集まらない。SNSを活用したり、社員の魅力を積極的に発信するなど、地道な活動が必要だと感じています。」\",\n      \"lesson\": \"知名度が低い企業は、積極的に情報発信を行い、企業の魅力をアピールする必要がある。社員のエンゲージメントを高め、口コミを広げることも有効。\"\n    }\n  ],\n  \"emotional_hooks\": [\n    \"「なぜ、あなたの会社には優秀な営業マンが集まらないのか？その根本原因を脳科学で解き明かします。」\",\n    \"「採用コストを30%削減し、定着率を2倍にする。そんな魔法のような採用戦略が存在します。」\",\n    \"「もう、履歴書とにらめっこする日々は終わりにしましょう。AIと脳科学を活用した、全く新しい採用戦略とは？」\n  ]\n}\n```",
  "parsed_data": {
    "emotional_analysis": {
      "primary_emotion": "焦り",
      "secondary_emotions": [
        "不安",
        "疲労"
      ],
      "pain_points": [
        "優秀な営業人材をなかなか採用できない",
        "採用してもすぐに辞めてしまう",
        "採用コストばかりがかさんで成果が出ない"
      ],
      "desires": [
        "自社の成長を加速させる優秀な営業チームを構築したい",
        "採用活動にかかる時間と労力を大幅に削減したい",
        "社員が長く活躍できる、魅力的な企業文化を醸成したい"
      ]
    },
    "human_touch_patterns": [
      {
        "type": "experience",
        "content": "「先日、ある企業の人事担当者の方とお話する機会がありました。『もう何ヶ月も営業職の募集をかけているのに、応募が全然来なくて…』と、本当に困り果てた様子でした。話を聞いていると、まさに今、この記事を読んでいるあなたと同じ悩みを抱えているようでした。」",
        "placement_suggestion": "導入部分"
      },
      {
        "type": "emotion",
        "content": "「採用がうまくいかない状況が続くと、本当に精神的に疲弊してしまいますよね。毎日、履歴書とにらめっこしながら、本当に自社に合う人材はどこにいるんだろう…と、途方に暮れてしまう気持ち、痛いほどよく分かります。」",
        "placement_suggestion": "問題提起の後"
      },
      {
        "type": "empathy",
        "content": "「でも、諦めないでください。営業職の採用は決して不可能ではありません。少し視点を変え、戦略を練り直すことで、必ず突破口は見つかります。この記事では、あなたの会社にぴったりの営業人材を見つけるためのヒントを、脳科学と行動経済学の視点も交えながら、具体的にお伝えしていきます。」",
        "placement_suggestion": "解決策の前"
      }
    ],
    "experience_episodes": [
      {
        "scenario": "中小企業の人事担当者が、なかなか営業職を採用できず、社長から毎日のようにプレッシャーをかけられている。",
        "narrative": "「社長からは『早く売上を上げられる人材を連れてこい！』と毎日怒鳴られる日々。求人広告の費用も底をつきそうで、正直、もうどうすればいいのか…。」",
        "lesson": "採用活動は、経営戦略と密接に連携している必要がある。現場の状況を理解し、適切な予算とサポート体制を整えることが重要。"
      },
      {
        "scenario": "大手企業の人事担当者が、高給を提示しても、優秀な営業人材から選ばれない。",
        "narrative": "「給与や福利厚生はどこよりも良いはずなのに、なぜか優秀な人材はうちを選んでくれない。企業文化やキャリアパスが魅力的でないのかもしれない…。」",
        "lesson": "給与だけでは優秀な人材は惹きつけられない。企業の理念やビジョン、キャリアパス、ワークライフバランスなど、総合的な魅力が必要。"
      },
      {
        "scenario": "スタートアップ企業の人事担当者が、知名度の低さから、応募者が集まらない。",
        "narrative": "「大手企業に比べて、どうしても知名度が低いので、応募者が集まらない。SNSを活用したり、社員の魅力を積極的に発信するなど、地道な活動が必要だと感じています。」",
        "lesson": "知名度が低い企業は、積極的に情報発信を行い、企業の魅力をアピールする必要がある。社員のエンゲージメントを高め、口コミを広げることも有効。"
      }
    ],
    "emotional_hooks": [
      "「なぜ、あなたの会社には優秀な営業マンが集まらないのか？その根本原因を脳科学で解き明かします。」",
      "「採用コストを30%削減し、定着率を2倍にする。そんな魔法のような採用戦略が存在します。」"
    ]
  },
  "metadata": {
    "generated_at": "2026-02-03T11:42:00.779215",
    "model": "gemini-2.0-flash",
    "model_config": {
      "platform": "gemini",
      "model": "gemini-2.0-flash"
    },
    "input_files": [
      "step0",
      "step1",
      "step3a",
      "step3b",
      "step3c",
      "step1_5"
    ]
  },
  "quality": {
    "attempts": 1,
    "issues": []
  },
  "token_usage": {
    "input": 15857,
    "output": 952
  },
  "output_path": "storage/dev-tenant-001/ca9bed12-f1fd-41a6-95b3-43e3fe74c238/step3_5/output.json",
  "output_digest": "4e09006f5a062f4f"
}