{
  "step": "step3_5",
  "keyword": "営業採用難しい",
  "emotional_analysis": {
    "primary_emotion": "焦燥感",
    "secondary_emotions": [
      "不安",
      "疲労感",
      "閉塞感"
    ],
    "pain_points": [
      "応募者が集まらない焦り",
      "採用してもすぐに辞めてしまうことへの落胆",
      "採用コストばかりが増えていくことへの危機感",
      "上司や経営層からのプレッシャー"
    ],
    "desires": [
      "優秀な営業人材を確実に採用したい",
      "採用活動にかかる時間とコストを削減したい",
      "採用した人材に長く活躍してほしい",
      "採用戦略が正しいと自信を持って言えるようになりたい"
    ]
  },
  "human_touch_patterns": [
    {
      "type": "experience",
      "content": "「先日も、期待していた応募者が面接に来なかったんです…」と、山田さんのような人事担当者が抱えるリアルな状況を冒頭で描写し、共感を誘う。",
      "placement_suggestion": "導入部分"
    },
    {
      "type": "emotion",
      "content": "「『またダメか…』と肩を落とす日々。優秀な人材はどこにいるんだろう、と途方に暮れてしまいますよね。」と、読者の抱える不安や疲労感に寄り添う言葉を添える。",
      "placement_suggestion": "問題提起の後"
    },
    {
      "type": "empathy",
      "content": "「でも、諦めないでください。必ず突破口はあります。私も同じように悩んでいた時期がありましたが、ある方法を試したところ、状況が大きく変わったんです。」と、共感を示しつつ、希望を与える。",
      "placement_suggestion": "解決策の前"
    }
  ],
  "experience_episodes": [
    {
      "scenario": "採用面接で、スキルは申し分ない応募者に出会った",
      "narrative": "「面接では受け答えも完璧で、即戦力として期待できると思ったんです。しかし、内定を出しても承諾してもらえず…。理由を聞くと、社風が合わないと感じたとのことでした。スキルだけでなく、企業文化とのマッチングも重要だと痛感しました。」",
      "lesson": "スキルだけでなく、企業文化とのマッチングが重要。"
    },
    {
      "scenario": "採用コスト削減のために、新しい採用手法を導入した",
      "narrative": "「ダイレクトリクルーティングを導入したのですが、なかなか効果が出ず…。結局、スカウトメールを送るだけで時間が過ぎていきました。ターゲット設定が曖昧だったこと、魅力的なメッセージを作成できていなかったことが原因だと気づきました。」",
      "lesson": "新しい採用手法を導入する際は、明確なターゲット設定と魅力的なメッセージが不可欠。"
    },
    {
      "scenario": "早期離職を防ぐために、入社後のフォロー体制を強化した",
      "narrative": "「メンター制度を導入し、新入社員一人ひとりに先輩社員をつけました。定期的な面談や相談の機会を設けたことで、新入社員の不安を軽減し、早期離職を防ぐことができました。コミュニケーションの重要性を改めて認識しました。」",
      "lesson": "入社後のフォロー体制強化は、新入社員の不安軽減と早期離職防止に効果的。"
    }
  ],
  "emotional_hooks": [
    "「なぜ、あなたの会社の営業採用はうまくいかないのか？ その根本原因を徹底解剖！」",
    "「【人事担当者必見】もう、一人で悩まないで！ 営業採用成功への道しるべ、ここにあります。」"
  ],
  "phase_emotional_map": {
    "phase1": {
      "dominant_emotion": "",
      "empathy_statements": [],
      "experience_episodes": []
    },
    "phase2": {
      "dominant_emotion": "",
      "empathy_statements": [],
      "experience_episodes": []
    },
    "phase3": {
      "dominant_emotion": "",
      "empathy_statements": [],
      "experience_episodes": []
    }
  },
  "behavioral_economics_hooks": {
    "loss_aversion_hook": "",
    "social_proof_hook": "",
    "authority_hook": "",
    "scarcity_hook": ""
  },
  "placement_instructions": [],
  "raw_output": "```json\n{\n  \"emotional_analysis\": {\n    \"primary_emotion\": \"焦燥感\",\n    \"secondary_emotions\": [\"不安\", \"疲労感\", \"閉塞感\"],\n    \"pain_points\": [\"応募者が集まらない焦り\", \"採用してもすぐに辞めてしまうことへの落胆\", \"採用コストばかりが増えていくことへの危機感\", \"上司や経営層からのプレッシャー\"],\n    \"desires\": [\"優秀な営業人材を確実に採用したい\", \"採用活動にかかる時間とコストを削減したい\", \"採用した人材に長く活躍してほしい\", \"採用戦略が正しいと自信を持って言えるようになりたい\"]\n  },\n  \"human_touch_patterns\": [\n    {\n      \"type\": \"experience\",\n      \"content\": \"「先日も、期待していた応募者が面接に来なかったんです…」と、山田さんのような人事担当者が抱えるリアルな状況を冒頭で描写し、共感を誘う。\",\n      \"placement_suggestion\": \"導入部分\"\n    },\n    {\n      \"type\": \"emotion\",\n      \"content\": \"「『またダメか…』と肩を落とす日々。優秀な人材はどこにいるんだろう、と途方に暮れてしまいますよね。」と、読者の抱える不安や疲労感に寄り添う言葉を添える。\",\n      \"placement_suggestion\": \"問題提起の後\"\n    },\n    {\n      \"type\": \"empathy\",\n      \"content\": \"「でも、諦めないでください。必ず突破口はあります。私も同じように悩んでいた時期がありましたが、ある方法を試したところ、状況が大きく変わったんです。」と、共感を示しつつ、希望を与える。\",\n      \"placement_suggestion\": \"解決策の前\"\n    }\n  ],\n  \"experience_episodes\": [\n    {\n      \"scenario\": \"採用面接で、スキルは申し分ない応募者に出会った\",\n      \"narrative\": \"「面接では受け答えも完璧で、即戦力として期待できると思ったんです。しかし、内定を出しても承諾してもらえず…。理由を聞くと、社風が合わないと感じたとのことでした。スキルだけでなく、企業文化とのマッチングも重要だと痛感しました。」\",\n      \"lesson\": \"スキルだけでなく、企業文化とのマッチングが重要。\"\n    },\n    {\n      \"scenario\": \"採用コスト削減のために、新しい採用手法を導入した\",\n      \"narrative\": \"「ダイレクトリクルーティングを導入したのですが、なかなか効果が出ず…。結局、スカウトメールを送るだけで時間が過ぎていきました。ターゲット設定が曖昧だったこと、魅力的なメッセージを作成できていなかったことが原因だと気づきました。」\",\n      \"lesson\": \"新しい採用手法を導入する際は、明確なターゲット設定と魅力的なメッセージが不可欠。\"\n    },\n    {\n      \"scenario\": \"早期離職を防ぐために、入社後のフォロー体制を強化した\",\n      \"narrative\": \"「メンター制度を導入し、新入社員一人ひとりに先輩社員をつけました。定期的な面談や相談の機会を設けたことで、新入社員の不安を軽減し、早期離職を防ぐことができました。コミュニケーションの重要性を改めて認識しました。」\",\n      \"lesson\": \"入社後のフォロー体制強化は、新入社員の不安軽減と早期離職防止に効果的。\"\n    }\n  ],\n  \"emotional_hooks\": [\n    \"「なぜ、あなたの会社の営業採用はうまくいかないのか？ その根本原因を徹底解剖！」\",\n    \"「【人事担当者必見】もう、一人で悩まないで！ 営業採用成功への道しるべ、ここにあります。」\",\n    \"「採用コスト30%削減も夢じゃない！ 脳科学に基づいた、革新的な採用戦略とは？」\n  ]\n}\n```",
  "parsed_data": {
    "emotional_analysis": {
      "primary_emotion": "焦燥感",
      "secondary_emotions": [
        "不安",
        "疲労感",
        "閉塞感"
      ],
      "pain_points": [
        "応募者が集まらない焦り",
        "採用してもすぐに辞めてしまうことへの落胆",
        "採用コストばかりが増えていくことへの危機感",
        "上司や経営層からのプレッシャー"
      ],
      "desires": [
        "優秀な営業人材を確実に採用したい",
        "採用活動にかかる時間とコストを削減したい",
        "採用した人材に長く活躍してほしい",
        "採用戦略が正しいと自信を持って言えるようになりたい"
      ]
    },
    "human_touch_patterns": [
      {
        "type": "experience",
        "content": "「先日も、期待していた応募者が面接に来なかったんです…」と、山田さんのような人事担当者が抱えるリアルな状況を冒頭で描写し、共感を誘う。",
        "placement_suggestion": "導入部分"
      },
      {
        "type": "emotion",
        "content": "「『またダメか…』と肩を落とす日々。優秀な人材はどこにいるんだろう、と途方に暮れてしまいますよね。」と、読者の抱える不安や疲労感に寄り添う言葉を添える。",
        "placement_suggestion": "問題提起の後"
      },
      {
        "type": "empathy",
        "content": "「でも、諦めないでください。必ず突破口はあります。私も同じように悩んでいた時期がありましたが、ある方法を試したところ、状況が大きく変わったんです。」と、共感を示しつつ、希望を与える。",
        "placement_suggestion": "解決策の前"
      }
    ],
    "experience_episodes": [
      {
        "scenario": "採用面接で、スキルは申し分ない応募者に出会った",
        "narrative": "「面接では受け答えも完璧で、即戦力として期待できると思ったんです。しかし、内定を出しても承諾してもらえず…。理由を聞くと、社風が合わないと感じたとのことでした。スキルだけでなく、企業文化とのマッチングも重要だと痛感しました。」",
        "lesson": "スキルだけでなく、企業文化とのマッチングが重要。"
      },
      {
        "scenario": "採用コスト削減のために、新しい採用手法を導入した",
        "narrative": "「ダイレクトリクルーティングを導入したのですが、なかなか効果が出ず…。結局、スカウトメールを送るだけで時間が過ぎていきました。ターゲット設定が曖昧だったこと、魅力的なメッセージを作成できていなかったことが原因だと気づきました。」",
        "lesson": "新しい採用手法を導入する際は、明確なターゲット設定と魅力的なメッセージが不可欠。"
      },
      {
        "scenario": "早期離職を防ぐために、入社後のフォロー体制を強化した",
        "narrative": "「メンター制度を導入し、新入社員一人ひとりに先輩社員をつけました。定期的な面談や相談の機会を設けたことで、新入社員の不安を軽減し、早期離職を防ぐことができました。コミュニケーションの重要性を改めて認識しました。」",
        "lesson": "入社後のフォロー体制強化は、新入社員の不安軽減と早期離職防止に効果的。"
      }
    ],
    "emotional_hooks": [
      "「なぜ、あなたの会社の営業採用はうまくいかないのか？ その根本原因を徹底解剖！」",
      "「【人事担当者必見】もう、一人で悩まないで！ 営業採用成功への道しるべ、ここにあります。」"
    ]
  },
  "metadata": {
    "generated_at": "2026-02-03T13:47:14.731799",
    "model": "gemini-2.0-flash",
    "model_config": {
      "platform": "gemini",
      "model": "gemini-2.0-flash"
    },
    "input_files": [
      "step0",
      "step1",
      "step3a",
      "step3b",
      "step3c",
      "step1_5"
    ]
  },
  "quality": {
    "attempts": 1,
    "issues": []
  },
  "token_usage": {
    "input": 16456,
    "output": 858
  },
  "output_path": "storage/dev-tenant-001/90dcfdc4-ebc1-4746-a09f-a9476d268565/step3_5/output.json",
  "output_digest": "80868c08fb72bd3a"
}