{
  "step": "step3_5",
  "keyword": "トラックドライバー 求人 書き方",
  "emotional_analysis": {
    "primary_emotion": "焦燥感と徒労感",
    "secondary_emotions": [
      "自社の魅力に対する自信喪失",
      "ネット採用ツールへの苦手意識・困惑",
      "経営者としての孤独な責任感"
    ],
    "pain_points": [
      "求人を出しても電話が鳴らない静寂の恐怖",
      "「給料が安いから来ないんだ」という諦めと、無理して上げられない現実の板挟み",
      "配車や経理など多忙な業務の合間を縫って求人を書く時間的・精神的余裕のなさ"
    ],
    "desires": [
      "「ウチの会社も悪くないな」と思ってくれるドライバーと出会いたい",
      "小手先のテクニックだけでなく、自社の本当の良さを言語化して自信を取り戻したい",
      "採用活動を成功させて、社長自らがハンドルを握る穴埋め業務から解放されたい"
    ]
  },
  "human_touch_patterns": [
    {
      "type": "experience",
      "content": "「求人掲載ボタンを押して3日。管理画面の応募数は『0』のまま。スマホを握りしめて『なぜだ？』とため息をついた経験、ありませんか？」という、誰もが経験する孤独な瞬間の描写。",
      "placement_suggestion": "導入部分（Phase 1：不安・課題認識）"
    },
    {
      "type": "empathy",
      "content": "「『アットホームな職場です』。そう書きたくなる気持ち、痛いほど分かります。実際に社長と社員の距離が近く、BBQも盛り上がる。それは嘘ではないはずです。しかし、残念ながらその温かさは、会ったことのない求職者には『ブラックの隠れ蓑』に見えてしまう残酷な現実があります。」",
      "placement_suggestion": "NG例の解説部分（Phase 2：理解・納得）"
    },
    {
      "type": "emotion",
      "content": "「大手のような高待遇は出せないかもしれない。新車ばかり揃えられないかもしれない。それでも、『毎日家に帰れる』『無理な配車は組まない』という社長の誠意は、書き方一つで必ず届きます。」",
      "placement_suggestion": "解決策・テンプレート提示の直前（Phase 2：理解・納得）"
    }
  ],
  "experience_episodes": [
    {
      "scenario": "面接当日のドタキャン",
      "narrative": "「履歴書も良し、電話の感じも良し。『この人なら即戦力だ』と期待して事務所を掃除し、お茶まで用意して待っていた面接時間。約束の時間を15分過ぎても現れず、電話も繋がらない。あの瞬間の脱力感は、何度味わっても慣れるものではありません。」",
      "lesson": "求人原稿の時点で「会社のリアル」を伝えきれていないと、応募者は軽い気持ちでボタンを押し、直前で不安になって辞退してしまう（ミスマッチの防止）。"
    },
    {
      "scenario": "既存ドライバーからの不満",
      "narrative": "「『社長、新しい人まだ入らないんですか？俺のシフト、もう限界ですよ』。長年支えてくれているベテラン社員からの悲鳴。申し訳なさと焦りで胃が痛くなる日々。彼らを守るためにも、採用は待ったなしの経営課題です。」",
      "lesson": "採用は単なる人員補充ではなく、今いる大切な社員を守るための「投資」である（行動への動機付け）。"
    }
  ],
  "emotional_hooks": [
    "「トラック1台が駐車場で眠るたび、月に◯◯万円の利益が静かに消えていく音に耳を塞いでいませんか？」",
    "「あなたの会社の魅力がないのではありません。その魅力が『ドライバー語』に翻訳されていないだけなのです。」",
    "「『どうせウチなんて』と諦める前に、あと1回だけ、書き方を変えて勝負してみませんか？これは、同じ規模の運送会社がV字回復した実話です。」"
  ],
  "phase_emotional_map": {
    "phase1": {
      "dominant_emotion": "",
      "empathy_statements": [],
      "experience_episodes": []
    },
    "phase2": {
      "dominant_emotion": "",
      "empathy_statements": [],
      "experience_episodes": []
    },
    "phase3": {
      "dominant_emotion": "",
      "empathy_statements": [],
      "experience_episodes": []
    }
  },
  "behavioral_economics_hooks": {
    "loss_aversion_hook": "",
    "social_proof_hook": "",
    "authority_hook": "",
    "scarcity_hook": ""
  },
  "placement_instructions": [],
  "raw_output": "ご提供いただいたペルソナ情報、競合分析、共起キーワードに基づき、読者（運送会社社長・採用担当者）の心に深く刺さる「人間味」のある要素を生成しました。\n\n```json\n{\n  \"emotional_analysis\": {\n    \"primary_emotion\": \"焦燥感と徒労感\",\n    \"secondary_emotions\": [\n      \"自社の魅力に対する自信喪失\",\n      \"ネット採用ツールへの苦手意識・困惑\",\n      \"経営者としての孤独な責任感\"\n    ],\n    \"pain_points\": [\n      \"求人を出しても電話が鳴らない静寂の恐怖\",\n      \"「給料が安いから来ないんだ」という諦めと、無理して上げられない現実の板挟み\",\n      \"配車や経理など多忙な業務の合間を縫って求人を書く時間的・精神的余裕のなさ\"\n    ],\n    \"desires\": [\n      \"「ウチの会社も悪くないな」と思ってくれるドライバーと出会いたい\",\n      \"小手先のテクニックだけでなく、自社の本当の良さを言語化して自信を取り戻したい\",\n      \"採用活動を成功させて、社長自らがハンドルを握る穴埋め業務から解放されたい\"\n    ]\n  },\n  \"human_touch_patterns\": [\n    {\n      \"type\": \"experience\",\n      \"content\": \"「求人掲載ボタンを押して3日。管理画面の応募数は『0』のまま。スマホを握りしめて『なぜだ？』とため息をついた経験、ありませんか？」という、誰もが経験する孤独な瞬間の描写。\",\n      \"placement_suggestion\": \"導入部分（Phase 1：不安・課題認識）\"\n    },\n    {\n      \"type\": \"empathy\",\n      \"content\": \"「『アットホームな職場です』。そう書きたくなる気持ち、痛いほど分かります。実際に社長と社員の距離が近く、BBQも盛り上がる。それは嘘ではないはずです。しかし、残念ながらその温かさは、会ったことのない求職者には『ブラックの隠れ蓑』に見えてしまう残酷な現実があります。」\",\n      \"placement_suggestion\": \"NG例の解説部分（Phase 2：理解・納得）\"\n    },\n    {\n      \"type\": \"emotion\",\n      \"content\": \"「大手のような高待遇は出せないかもしれない。新車ばかり揃えられないかもしれない。それでも、『毎日家に帰れる』『無理な配車は組まない』という社長の誠意は、書き方一つで必ず届きます。」\",\n      \"placement_suggestion\": \"解決策・テンプレート提示の直前（Phase 2：理解・納得）\"\n    }\n  ],\n  \"experience_episodes\": [\n    {\n      \"scenario\": \"面接当日のドタキャン\",\n      \"narrative\": \"「履歴書も良し、電話の感じも良し。『この人なら即戦力だ』と期待して事務所を掃除し、お茶まで用意して待っていた面接時間。約束の時間を15分過ぎても現れず、電話も繋がらない。あの瞬間の脱力感は、何度味わっても慣れるものではありません。」\",\n      \"lesson\": \"求人原稿の時点で「会社のリアル」を伝えきれていないと、応募者は軽い気持ちでボタンを押し、直前で不安になって辞退してしまう（ミスマッチの防止）。\"\n    },\n    {\n      \"scenario\": \"既存ドライバーからの不満\",\n      \"narrative\": \"「『社長、新しい人まだ入らないんですか？俺のシフト、もう限界ですよ』。長年支えてくれているベテラン社員からの悲鳴。申し訳なさと焦りで胃が痛くなる日々。彼らを守るためにも、採用は待ったなしの経営課題です。」\",\n      \"lesson\": \"採用は単なる人員補充ではなく、今いる大切な社員を守るための「投資」である（行動への動機付け）。\"\n    }\n  ],\n  \"emotional_hooks\": [\n    \"「トラック1台が駐車場で眠るたび、月に◯◯万円の利益が静かに消えていく音に耳を塞いでいませんか？」\",\n    \"「あなたの会社の魅力がないのではありません。その魅力が『ドライバー語』に翻訳されていないだけなのです。」\",\n    \"「『どうせウチなんて』と諦める前に、あと1回だけ、書き方を変えて勝負してみませんか？これは、同じ規模の運送会社がV字回復した実話です。」\"\n  ]\n}\n```",
  "parsed_data": {
    "emotional_analysis": {
      "primary_emotion": "焦燥感と徒労感",
      "secondary_emotions": [
        "自社の魅力に対する自信喪失",
        "ネット採用ツールへの苦手意識・困惑",
        "経営者としての孤独な責任感"
      ],
      "pain_points": [
        "求人を出しても電話が鳴らない静寂の恐怖",
        "「給料が安いから来ないんだ」という諦めと、無理して上げられない現実の板挟み",
        "配車や経理など多忙な業務の合間を縫って求人を書く時間的・精神的余裕のなさ"
      ],
      "desires": [
        "「ウチの会社も悪くないな」と思ってくれるドライバーと出会いたい",
        "小手先のテクニックだけでなく、自社の本当の良さを言語化して自信を取り戻したい",
        "採用活動を成功させて、社長自らがハンドルを握る穴埋め業務から解放されたい"
      ]
    },
    "human_touch_patterns": [
      {
        "type": "experience",
        "content": "「求人掲載ボタンを押して3日。管理画面の応募数は『0』のまま。スマホを握りしめて『なぜだ？』とため息をついた経験、ありませんか？」という、誰もが経験する孤独な瞬間の描写。",
        "placement_suggestion": "導入部分（Phase 1：不安・課題認識）"
      },
      {
        "type": "empathy",
        "content": "「『アットホームな職場です』。そう書きたくなる気持ち、痛いほど分かります。実際に社長と社員の距離が近く、BBQも盛り上がる。それは嘘ではないはずです。しかし、残念ながらその温かさは、会ったことのない求職者には『ブラックの隠れ蓑』に見えてしまう残酷な現実があります。」",
        "placement_suggestion": "NG例の解説部分（Phase 2：理解・納得）"
      },
      {
        "type": "emotion",
        "content": "「大手のような高待遇は出せないかもしれない。新車ばかり揃えられないかもしれない。それでも、『毎日家に帰れる』『無理な配車は組まない』という社長の誠意は、書き方一つで必ず届きます。」",
        "placement_suggestion": "解決策・テンプレート提示の直前（Phase 2：理解・納得）"
      }
    ],
    "experience_episodes": [
      {
        "scenario": "面接当日のドタキャン",
        "narrative": "「履歴書も良し、電話の感じも良し。『この人なら即戦力だ』と期待して事務所を掃除し、お茶まで用意して待っていた面接時間。約束の時間を15分過ぎても現れず、電話も繋がらない。あの瞬間の脱力感は、何度味わっても慣れるものではありません。」",
        "lesson": "求人原稿の時点で「会社のリアル」を伝えきれていないと、応募者は軽い気持ちでボタンを押し、直前で不安になって辞退してしまう（ミスマッチの防止）。"
      },
      {
        "scenario": "既存ドライバーからの不満",
        "narrative": "「『社長、新しい人まだ入らないんですか？俺のシフト、もう限界ですよ』。長年支えてくれているベテラン社員からの悲鳴。申し訳なさと焦りで胃が痛くなる日々。彼らを守るためにも、採用は待ったなしの経営課題です。」",
        "lesson": "採用は単なる人員補充ではなく、今いる大切な社員を守るための「投資」である（行動への動機付け）。"
      }
    ],
    "emotional_hooks": [
      "「トラック1台が駐車場で眠るたび、月に◯◯万円の利益が静かに消えていく音に耳を塞いでいませんか？」",
      "「あなたの会社の魅力がないのではありません。その魅力が『ドライバー語』に翻訳されていないだけなのです。」",
      "「『どうせウチなんて』と諦める前に、あと1回だけ、書き方を変えて勝負してみませんか？これは、同じ規模の運送会社がV字回復した実話です。」"
    ]
  },
  "metadata": {
    "generated_at": "2026-02-04T03:49:08.051498",
    "model": "gemini-3-pro-preview",
    "model_config": {
      "platform": "gemini",
      "model": "gemini-3-pro-preview"
    },
    "input_files": [
      "step0",
      "step1",
      "step3a",
      "step3b",
      "step3c",
      "step1_5"
    ]
  },
  "quality": {
    "attempts": 1,
    "issues": []
  },
  "token_usage": {
    "input": 19042,
    "output": 1029
  },
  "output_path": "storage/dev-tenant-001/460ee6fe-60bb-4454-83f9-30be3232b345/step3_5/output.json",
  "output_digest": "ce48e60106086b3b"
}