{
  "step": "step3_5",
  "keyword": "自動車整備士 採用難しい",
  "emotional_analysis": {
    "primary_emotion": "不安",
    "secondary_emotions": [
      "焦り",
      "疲労",
      "孤独"
    ],
    "pain_points": [
      "求人広告費ばかりがかさみ、応募が来ない、もしくは質が低い",
      "若手が入社してもすぐに辞めてしまい、育成コストが無駄になる",
      "慢性的な整備士不足で、従業員の残業が増え、顧客からのクレームも増えている",
      "最新技術に対応できる人材が不足しており、将来への不安を感じている"
    ],
    "desires": [
      "優秀な自動車整備士を安定的に採用したい",
      "若手が長く定着し、技術を継承してくれるような職場環境を築きたい",
      "整備士の負担を減らし、顧客満足度を向上させたい",
      "最新技術に対応できる人材を育成し、未来に繋がる整備工場を作りたい"
    ]
  },
  "human_touch_patterns": [
    {
      "type": "experience",
      "content": "田中人事部長が実際に経験した、採用活動の苦労や失敗談を語る形式で導入する。",
      "placement_suggestion": "記事の冒頭。読者の共感を呼ぶため。"
    },
    {
      "type": "emotion",
      "content": "「せっかく採用してもすぐに辞めてしまうと、本当に心が折れますよね。」といった、読者の感情に寄り添う言葉を問題提起の後に加える。",
      "placement_suggestion": "採用難の現状を説明した後。読者の気持ちを代弁する。"
    },
    {
      "type": "empathy",
      "content": "「同じように悩んでいる人事担当者の方々へ、少しでもお役に立てれば幸いです。」といった、共感を示すフレーズを解決策の前に挿入する。",
      "placement_suggestion": "具体的な対策を提示する前。読者の不安を和らげる。"
    }
  ],
  "experience_episodes": [
    {
      "scenario": "求人広告を出稿したが、全く応募がなかった時",
      "narrative": "以前、期待を込めて高額な求人広告を出したんです。でも、応募はゼロ。広告代理店に文句を言っても、『今はどこも同じですよ』と言われる始末。本当に悔しくて、情けなかったですね。",
      "lesson": "求人広告だけに頼るのではなく、多角的な採用戦略が必要だと痛感した。"
    },
    {
      "scenario": "せっかく採用した若手が、３ヶ月で辞めてしまった時",
      "narrative": "やっとの思いで採用できた若手整備士が、３ヶ月で『やっぱり自分には合わない』と辞めてしまった時は、本当にショックでした。OJTにかけた時間と労力が全て無駄になった気がしました。",
      "lesson": "採用後のフォローアップ体制や、キャリアパスの明確化が重要だと学んだ。"
    }
  ],
  "emotional_hooks": [
    "「採用費をドブに捨てるのは、もう終わりにしませんか？」",
    "「整備士不足で、あなたの会社は年間いくら損していますか？」"
  ],
  "phase_emotional_map": {
    "phase1": {
      "dominant_emotion": "",
      "empathy_statements": [],
      "experience_episodes": []
    },
    "phase2": {
      "dominant_emotion": "",
      "empathy_statements": [],
      "experience_episodes": []
    },
    "phase3": {
      "dominant_emotion": "",
      "empathy_statements": [],
      "experience_episodes": []
    }
  },
  "behavioral_economics_hooks": {
    "loss_aversion_hook": "",
    "social_proof_hook": "",
    "authority_hook": "",
    "scarcity_hook": ""
  },
  "placement_instructions": [],
  "raw_output": "```json\n{\n  \"emotional_analysis\": {\n    \"primary_emotion\": \"不安\",\n    \"secondary_emotions\": [\"焦り\", \"疲労\", \"孤独\"],\n    \"pain_points\": [\n      \"求人広告費ばかりがかさみ、応募が来ない、もしくは質が低い\",\n      \"若手が入社してもすぐに辞めてしまい、育成コストが無駄になる\",\n      \"慢性的な整備士不足で、従業員の残業が増え、顧客からのクレームも増えている\",\n      \"最新技術に対応できる人材が不足しており、将来への不安を感じている\"\n    ],\n    \"desires\": [\n      \"優秀な自動車整備士を安定的に採用したい\",\n      \"若手が長く定着し、技術を継承してくれるような職場環境を築きたい\",\n      \"整備士の負担を減らし、顧客満足度を向上させたい\",\n      \"最新技術に対応できる人材を育成し、未来に繋がる整備工場を作りたい\"\n    ]\n  },\n  \"human_touch_patterns\": [\n    {\n      \"type\": \"experience\",\n      \"content\": \"田中人事部長が実際に経験した、採用活動の苦労や失敗談を語る形式で導入する。\",\n      \"placement_suggestion\": \"記事の冒頭。読者の共感を呼ぶため。\"\n    },\n    {\n      \"type\": \"emotion\",\n      \"content\": \"「せっかく採用してもすぐに辞めてしまうと、本当に心が折れますよね。」といった、読者の感情に寄り添う言葉を問題提起の後に加える。\",\n      \"placement_suggestion\": \"採用難の現状を説明した後。読者の気持ちを代弁する。\"\n    },\n    {\n      \"type\": \"empathy\",\n      \"content\": \"「同じように悩んでいる人事担当者の方々へ、少しでもお役に立てれば幸いです。」といった、共感を示すフレーズを解決策の前に挿入する。\",\n      \"placement_suggestion\": \"具体的な対策を提示する前。読者の不安を和らげる。\"\n    }\n  ],\n  \"experience_episodes\": [\n    {\n      \"scenario\": \"求人広告を出稿したが、全く応募がなかった時\",\n      \"narrative\": \"以前、期待を込めて高額な求人広告を出したんです。でも、応募はゼロ。広告代理店に文句を言っても、『今はどこも同じですよ』と言われる始末。本当に悔しくて、情けなかったですね。\",\n      \"lesson\": \"求人広告だけに頼るのではなく、多角的な採用戦略が必要だと痛感した。\"\n    },\n    {\n      \"scenario\": \"せっかく採用した若手が、３ヶ月で辞めてしまった時\",\n      \"narrative\": \"やっとの思いで採用できた若手整備士が、３ヶ月で『やっぱり自分には合わない』と辞めてしまった時は、本当にショックでした。OJTにかけた時間と労力が全て無駄になった気がしました。\",\n      \"lesson\": \"採用後のフォローアップ体制や、キャリアパスの明確化が重要だと学んだ。\"\n    }\n  ],\n  \"emotional_hooks\": [\n    \"「採用費をドブに捨てるのは、もう終わりにしませんか？」\",\n    \"「整備士不足で、あなたの会社は年間いくら損していますか？」\",\n    \"「定着率アップの秘訣：社員が『ここで働きたい！』と思える職場を作るには？」\n  ]\n}\n```",
  "parsed_data": {
    "emotional_analysis": {
      "primary_emotion": "不安",
      "secondary_emotions": [
        "焦り",
        "疲労",
        "孤独"
      ],
      "pain_points": [
        "求人広告費ばかりがかさみ、応募が来ない、もしくは質が低い",
        "若手が入社してもすぐに辞めてしまい、育成コストが無駄になる",
        "慢性的な整備士不足で、従業員の残業が増え、顧客からのクレームも増えている",
        "最新技術に対応できる人材が不足しており、将来への不安を感じている"
      ],
      "desires": [
        "優秀な自動車整備士を安定的に採用したい",
        "若手が長く定着し、技術を継承してくれるような職場環境を築きたい",
        "整備士の負担を減らし、顧客満足度を向上させたい",
        "最新技術に対応できる人材を育成し、未来に繋がる整備工場を作りたい"
      ]
    },
    "human_touch_patterns": [
      {
        "type": "experience",
        "content": "田中人事部長が実際に経験した、採用活動の苦労や失敗談を語る形式で導入する。",
        "placement_suggestion": "記事の冒頭。読者の共感を呼ぶため。"
      },
      {
        "type": "emotion",
        "content": "「せっかく採用してもすぐに辞めてしまうと、本当に心が折れますよね。」といった、読者の感情に寄り添う言葉を問題提起の後に加える。",
        "placement_suggestion": "採用難の現状を説明した後。読者の気持ちを代弁する。"
      },
      {
        "type": "empathy",
        "content": "「同じように悩んでいる人事担当者の方々へ、少しでもお役に立てれば幸いです。」といった、共感を示すフレーズを解決策の前に挿入する。",
        "placement_suggestion": "具体的な対策を提示する前。読者の不安を和らげる。"
      }
    ],
    "experience_episodes": [
      {
        "scenario": "求人広告を出稿したが、全く応募がなかった時",
        "narrative": "以前、期待を込めて高額な求人広告を出したんです。でも、応募はゼロ。広告代理店に文句を言っても、『今はどこも同じですよ』と言われる始末。本当に悔しくて、情けなかったですね。",
        "lesson": "求人広告だけに頼るのではなく、多角的な採用戦略が必要だと痛感した。"
      },
      {
        "scenario": "せっかく採用した若手が、３ヶ月で辞めてしまった時",
        "narrative": "やっとの思いで採用できた若手整備士が、３ヶ月で『やっぱり自分には合わない』と辞めてしまった時は、本当にショックでした。OJTにかけた時間と労力が全て無駄になった気がしました。",
        "lesson": "採用後のフォローアップ体制や、キャリアパスの明確化が重要だと学んだ。"
      }
    ],
    "emotional_hooks": [
      "「採用費をドブに捨てるのは、もう終わりにしませんか？」",
      "「整備士不足で、あなたの会社は年間いくら損していますか？」"
    ]
  },
  "metadata": {
    "generated_at": "2026-02-03T11:42:00.763873",
    "model": "gemini-2.0-flash",
    "model_config": {
      "platform": "gemini",
      "model": "gemini-2.0-flash"
    },
    "input_files": [
      "step0",
      "step1",
      "step3a",
      "step3b",
      "step3c",
      "step1_5"
    ]
  },
  "quality": {
    "attempts": 1,
    "issues": []
  },
  "token_usage": {
    "input": 17201,
    "output": 774
  },
  "output_path": "storage/dev-tenant-001/67c73686-f144-42a5-b52c-96e02c1e04e6/step3_5/output.json",
  "output_digest": "cfd4ed35f105b158"
}